evrmore_rpc/__init__.py
evrmore_rpc/client.py
evrmore_rpc/client.pyi
evrmore_rpc/config.py
evrmore_rpc/stress_test.py
evrmore_rpc/utils.py
evrmore_rpc/models/__init__.py
evrmore_rpc/models/addressindex.py
evrmore_rpc/models/assets.py
evrmore_rpc/models/base.py
evrmore_rpc/models/blockchain.py
evrmore_rpc/models/mining.py
evrmore_rpc/models/network.py
evrmore_rpc/models/rawtransactions.py
evrmore_rpc/models/wallet.py
evrmore_rpc/zmq/__init__.py
evrmore_rpc/zmq/__init__.pyi
evrmore_rpc/zmq/client.py
evrmore_rpc/zmq/client.pyi
evrmore_rpc/zmq/models.py
evrmore_rpc/zmq/models.pyi
evrmore_rpc-4.0.3.dist-info/METADATA
evrmore_rpc-4.0.3.dist-info/WHEEL
evrmore_rpc-4.0.3.dist-info/entry_points.txt
evrmore_rpc-4.0.3.dist-info/licenses/LICENSE
evrmore_rpc-4.0.3.dist-info/RECORD
