Metadata-Version: 2.4
Name: evrmore-rpc
Version: 4.0.3
Summary: A high-performance Python wrapper for Evrmore blockchain RPC commands with a seamless API
Project-URL: Homepage, https://manticore.technology
Project-URL: Documentation, https://manticoretechnologies.github.io/evrmore-rpc-dev/
Project-URL: Repository, https://github.com/ManticoreTechnologies/evrmore-rpc-dev.git
Project-URL: Issues, https://github.com/ManticoreTechnologies/evrmore-rpc-dev/issues
Author-email: Manticore Technologies <info@manticore.tech>
License-Expression: MIT
License-File: LICENSE
Keywords: assets,async,blockchain,cryptocurrency,evrmore,rpc,seamless-api,wallet,zmq
Classifier: Development Status :: 5 - Production/Stable
Classifier: Intended Audience :: Developers
Classifier: License :: OSI Approved :: MIT License
Classifier: Programming Language :: Python :: 3
Classifier: Programming Language :: Python :: 3.8
Classifier: Programming Language :: Python :: 3.9
Classifier: Programming Language :: Python :: 3.10
Classifier: Programming Language :: Python :: 3.11
Classifier: Topic :: Software Development :: Libraries :: Python Modules
Classifier: Topic :: System :: Networking
Requires-Python: >=3.8
Requires-Dist: aiohttp>=3.8.0
Requires-Dist: pydantic>=2.0.0
Requires-Dist: pyzmq
Requires-Dist: requests>=2.28.0
Requires-Dist: rich
Provides-Extra: all
Requires-Dist: build; extra == 'all'
Requires-Dist: jinja2>=3.1.2; extra == 'all'
Requires-Dist: mkdocs-material>=9.5; extra == 'all'
Requires-Dist: mkdocs>=1.5; extra == 'all'
Requires-Dist: mkdocstrings[python]>=0.24; extra == 'all'
Requires-Dist: pytest-asyncio>=0.18.0; extra == 'all'
Requires-Dist: pytest>=7.0.0; extra == 'all'
Requires-Dist: setuptools; extra == 'all'
Requires-Dist: twine; extra == 'all'
Provides-Extra: dev
Requires-Dist: build; extra == 'dev'
Requires-Dist: pytest-asyncio>=0.18.0; extra == 'dev'
Requires-Dist: pytest>=7.0.0; extra == 'dev'
Requires-Dist: setuptools; extra == 'dev'
Requires-Dist: twine; extra == 'dev'
Provides-Extra: docs
Requires-Dist: jinja2>=3.1.2; extra == 'docs'
Requires-Dist: mkdocs-material>=9.5; extra == 'docs'
Requires-Dist: mkdocs>=1.5; extra == 'docs'
Requires-Dist: mkdocstrings[python]>=0.24; extra == 'docs'
